<?xml version="1.0" encoding="utf-8"?>
<!DOCTYPE hibernate-mapping PUBLIC "-//Hibernate/Hibernate Mapping DTD 3.0//EN"
"http://hibernate.sourceforge.net/hibernate-mapping-3.0.dtd">
<!-- 
    Mapping file autogenerated by MyEclipse Persistence Tools
-->
<hibernate-mapping>
    <class name="org.efood.vo.Orderitem" table="orderitem" catalog="efood">
        <id name="orderitemid" type="java.lang.Integer">
            <column name="orderitemid" />
            <generator class="native" />
        </id>
        <many-to-one name="menu" class="org.efood.vo.Menu" fetch="select" lazy="false">
            <column name="menuid" not-null="true" />
        </many-to-one>
        <many-to-one name="orders" class="org.efood.vo.Orders" fetch="select" lazy="false">
            <column name="orderid" not-null="true" />
        </many-to-one>
        <property name="quantity" type="java.lang.Integer">
            <column name="quantity" />
        </property>
        <property name="comment" type="java.lang.String">
            <column name="comment" />
        </property>
        <property name="status" type="java.lang.Integer">
            <column name="status" />
        </property>
    </class>
</hibernate-mapping>
